{
  "collapse-filter": true,
  "search": "",
  "showTags": false,
  "showAttachments": true,
  "hideUnresolved": false,
  "showOrphans": true,
  "collapse-color-groups": true,
  "colorGroups": [
    {
      "query": "path:\"Odoo/\"",
      "color": {
        "a": 1,
        "rgb": 5966438
      }
    },
    {
      "query": "path:\"BIT/\"",
      "color": {
        "a": 1,
        "rgb": 505351
      }
    },
    {
      "query": "path:\"Business/\"",
      "color": {
        "a": 1,
        "rgb": 16768517
      }
    },
    {
      "query": "path:\"IT/\"",
      "color": {
        "a": 1,
        "rgb": 1435105
      }
    }
  ],
  "collapse-display": true,
  "showArrow": true,
  "textFadeMultiplier": -3,
  "nodeSizeMultiplier": 1.19739583333333,
  "lineSizeMultiplier": 2.24375,
  "collapse-forces": false,
  "centerStrength": 0,
  "repelStrength": 6.5625,
  "linkStrength": 0.895833333333333,
  "linkDistance": 99,
  "scale": 0.104483372289413,
  "close": true
}